djsailthru
