Metadata-Version: 1.0
Name: djsailthru
Version: 0.0.6
Summary: 
